{
    "items": [
        {
            "pagePath": "/java-localdate-addition-subtraction/",
            "pv": "68"
        },
        {
            "pagePath": "/eclipse-line-problem/",
            "pv": "63"
        },
        {
            "pagePath": "/java-isdigit-method/",
            "pv": "53"
        },
        {
            "pagePath": "/java-tochararray/",
            "pv": "52"
        },
        {
            "pagePath": "/qualification-oraclemastersilversql/",
            "pv": "47"
        },
        {
            "pagePath": "/qualification-ap-pm/",
            "pv": "43"
        },
        {
            "pagePath": "/java-int-string-change/",
            "pv": "37"
        },
        {
            "pagePath": "/product-review-monitor-arm-desk/",
            "pv": "35"
        },
        {
            "pagePath": "/subversion-checksum-mismatch/",
            "pv": "25"
        },
        {
            "pagePath": "/java-shuffle-method/",
            "pv": "20"
        },
        {
            "pagePath": "/closedxml-image/",
            "pv": "18"
        },
        {
            "pagePath": "/java-isalphabetic-method/",
            "pv": "18"
        },
        {
            "pagePath": "/java-ceil-floor-round/",
            "pv": "17"
        },
        {
            "pagePath": "/googlecalendar-end-of-month/",
            "pv": "15"
        },
        {
            "pagePath": "/closedxml-image-property/",
            "pv": "13"
        },
        {
            "pagePath": "/windows-forms-scale/",
            "pv": "13"
        },
        {
            "pagePath": "/java-deletecharat-method/",
            "pv": "12"
        },
        {
            "pagePath": "/java-identity-equivalence/",
            "pv": "12"
        },
        {
            "pagePath": "/java-intern/",
            "pv": "12"
        },
        {
            "pagePath": "/c-language-compiler/",
            "pv": "11"
        },
        {
            "pagePath": "/java-mismatch-method/",
            "pv": "10"
        },
        {
            "pagePath": "/qualification-oraclemastersilverdba/",
            "pv": "10"
        },
        {
            "pagePath": "/java-localdate-period/",
            "pv": "9"
        },
        {
            "pagePath": "/java-tostring-deeptostring-method/",
            "pv": "9"
        },
        {
            "pagePath": "/qualification-ap-book/",
            "pv": "9"
        },
        {
            "pagePath": "/qualification-javasilverse11-measures/",
            "pv": "9"
        },
        {
            "pagePath": "/",
            "pv": "8"
        },
        {
            "pagePath": "/javasilver-se11-application/",
            "pv": "8"
        },
        {
            "pagePath": "/java-sqrt-method/",
            "pv": "7"
        },
        {
            "pagePath": "/qualification-javagold-se11/",
            "pv": "7"
        },
        {
            "pagePath": "/blog-access-problem/",
            "pv": "6"
        },
        {
            "pagePath": "/java-fibonacci-sequence/",
            "pv": "6"
        },
        {
            "pagePath": "/java-islowercase-method/",
            "pv": "6"
        },
        {
            "pagePath": "/qualification-oraclemastersilversql-measures/",
            "pv": "6"
        },
        {
            "pagePath": "/qualification-sc/",
            "pv": "6"
        },
        {
            "pagePath": "/vmware-monitor/",
            "pv": "6"
        },
        {
            "pagePath": "/game-ps5-apex/",
            "pv": "5"
        },
        {
            "pagePath": "/java-magic-square-4-4/",
            "pv": "5"
        },
        {
            "pagePath": "/java-method-function/",
            "pv": "5"
        },
        {
            "pagePath": "/java-pow-method/",
            "pv": "5"
        },
        {
            "pagePath": "/java-random-password/",
            "pv": "5"
        },
        {
            "pagePath": "/qualification-db/",
            "pv": "5"
        },
        {
            "pagePath": "/qualification-fe-kayanoki/",
            "pv": "5"
        },
        {
            "pagePath": "/qualification-sg-pass/",
            "pv": "5"
        },
        {
            "pagePath": "/blog-alt-setting/",
            "pv": "4"
        },
        {
            "pagePath": "/java-float-double/",
            "pv": "4"
        },
        {
            "pagePath": "/java-random-number/",
            "pv": "4"
        },
        {
            "pagePath": "/oracle-pearsonvue/",
            "pv": "4"
        },
        {
            "pagePath": "/qualification-ap-pass/",
            "pv": "4"
        },
        {
            "pagePath": "/android-translucent/",
            "pv": "3"
        },
        {
            "pagePath": "/archives/2024/02",
            "pv": "3"
        },
        {
            "pagePath": "/game-ps5-mixamp-hdmiadapter/",
            "pv": "3"
        },
        {
            "pagePath": "/github-actions-autocommit/",
            "pv": "3"
        },
        {
            "pagePath": "/java-browser-compile/",
            "pv": "3"
        },
        {
            "pagePath": "/java-mini-numberplace-1/",
            "pv": "3"
        },
        {
            "pagePath": "/java-sudoku-1/",
            "pv": "3"
        },
        {
            "pagePath": "/qualification-aws-clf/",
            "pv": "3"
        },
        {
            "pagePath": "/qualification-fe-pass/",
            "pv": "3"
        },
        {
            "pagePath": "/qualification-ip-fe-ap-pass/",
            "pv": "3"
        },
        {
            "pagePath": "/qualification-ip-merit/",
            "pv": "3"
        },
        {
            "pagePath": "/about",
            "pv": "2"
        },
        {
            "pagePath": "/android-room-primary-key/",
            "pv": "2"
        },
        {
            "pagePath": "/dbms-debug-vc2coll/",
            "pv": "2"
        },
        {
            "pagePath": "/game-trophy-2021-07-25/",
            "pv": "2"
        },
        {
            "pagePath": "/oracle-pearsonvue",
            "pv": "2"
        },
        {
            "pagePath": "/product-review-chair/",
            "pv": "2"
        },
        {
            "pagePath": "/product-review-logicool-k380/",
            "pv": "2"
        },
        {
            "pagePath": "/product-review-shure-aonic215/",
            "pv": "2"
        },
        {
            "pagePath": "/qualification-ap-pass",
            "pv": "2"
        },
        {
            "pagePath": "/qualification-javasilverse11/",
            "pv": "2"
        },
        {
            "pagePath": "/aws-clf-measures/",
            "pv": "1"
        },
        {
            "pagePath": "/domain-to-route53/",
            "pv": "1"
        },
        {
            "pagePath": "/hugo-docker/",
            "pv": "1"
        },
        {
            "pagePath": "/it-qualification",
            "pv": "1"
        },
        {
            "pagePath": "/profile",
            "pv": "1"
        },
        {
            "pagePath": "/qualification-aws-saa",
            "pv": "1"
        },
        {
            "pagePath": "/qualification-aws-saa/",
            "pv": "1"
        },
        {
            "pagePath": "/qualification-fe-cbt/",
            "pv": "1"
        },
        {
            "pagePath": "/qualification-oraclemastersilverdba",
            "pv": "1"
        },
        {
            "pagePath": "/qualification-oraclemastersilversql",
            "pv": "1"
        },
        {
            "pagePath": "/tags/java/",
            "pv": "1"
        },
        {
            "pagePath": "/tags/php/",
            "pv": "1"
        },
        {
            "pagePath": "/tags/svn/",
            "pv": "1"
        }
    ],
    "createdAt": "2025-04-12T03:21:13.773Z"
}