{
    "items": [
        {
            "pagePath": "/java-localdate-addition-subtraction/",
            "pv": "97"
        },
        {
            "pagePath": "/eclipse-line-problem/",
            "pv": "93"
        },
        {
            "pagePath": "/java-tochararray/",
            "pv": "78"
        },
        {
            "pagePath": "/java-int-string-change/",
            "pv": "59"
        },
        {
            "pagePath": "/qualification-oraclemastersilversql/",
            "pv": "43"
        },
        {
            "pagePath": "/java-isdigit-method/",
            "pv": "38"
        },
        {
            "pagePath": "/qualification-javasilverse11-measures/",
            "pv": "33"
        },
        {
            "pagePath": "/product-review-monitor-arm-desk/",
            "pv": "32"
        },
        {
            "pagePath": "/qualification-oraclemastersilversql-measures/",
            "pv": "30"
        },
        {
            "pagePath": "/blog-access-problem/",
            "pv": "25"
        },
        {
            "pagePath": "/java-shuffle-method/",
            "pv": "25"
        },
        {
            "pagePath": "/closedxml-image/",
            "pv": "23"
        },
        {
            "pagePath": "/java-ceil-floor-round/",
            "pv": "21"
        },
        {
            "pagePath": "/subversion-checksum-mismatch/",
            "pv": "21"
        },
        {
            "pagePath": "/java-mismatch-method/",
            "pv": "17"
        },
        {
            "pagePath": "/java-isalphabetic-method/",
            "pv": "15"
        },
        {
            "pagePath": "/googlecalendar-end-of-month/",
            "pv": "13"
        },
        {
            "pagePath": "/java-tostring-deeptostring-method/",
            "pv": "12"
        },
        {
            "pagePath": "/game-codmw2-warzone2-setting/",
            "pv": "11"
        },
        {
            "pagePath": "/java-intern/",
            "pv": "11"
        },
        {
            "pagePath": "/qualification-sg-pass/",
            "pv": "11"
        },
        {
            "pagePath": "/game-biohazard-re2/",
            "pv": "10"
        },
        {
            "pagePath": "/java-deletecharat-method/",
            "pv": "10"
        },
        {
            "pagePath": "/oracle-pearsonvue/",
            "pv": "10"
        },
        {
            "pagePath": "/game-codmw2-trophy/",
            "pv": "9"
        },
        {
            "pagePath": "/java-islowercase-method/",
            "pv": "9"
        },
        {
            "pagePath": "/java-random-password/",
            "pv": "9"
        },
        {
            "pagePath": "/qualification-ip-fe-ap-pass/",
            "pv": "9"
        },
        {
            "pagePath": "/qualification-oraclemastersilverdba/",
            "pv": "9"
        },
        {
            "pagePath": "/aws-saa-measures/",
            "pv": "8"
        },
        {
            "pagePath": "/java-float-double/",
            "pv": "8"
        },
        {
            "pagePath": "/javasilver-se11-application/",
            "pv": "8"
        },
        {
            "pagePath": "/qualification-aws-saa/",
            "pv": "8"
        },
        {
            "pagePath": "/qualification-javagold-se11/",
            "pv": "8"
        },
        {
            "pagePath": "/game-mixamp-apex-equalizer/",
            "pv": "7"
        },
        {
            "pagePath": "/game-ps5-apex/",
            "pv": "7"
        },
        {
            "pagePath": "/java-identity-equivalence/",
            "pv": "7"
        },
        {
            "pagePath": "/java-sqrt-method/",
            "pv": "7"
        },
        {
            "pagePath": "/java-localdate-period/",
            "pv": "6"
        },
        {
            "pagePath": "/qualification-javasilverse11/",
            "pv": "6"
        },
        {
            "pagePath": "/",
            "pv": "5"
        },
        {
            "pagePath": "/domain-to-route53/",
            "pv": "5"
        },
        {
            "pagePath": "/java-method-function/",
            "pv": "5"
        },
        {
            "pagePath": "/java-random-number/",
            "pv": "5"
        },
        {
            "pagePath": "/qualification-fe-cbt/",
            "pv": "5"
        },
        {
            "pagePath": "/qualification-fe-pass/",
            "pv": "5"
        },
        {
            "pagePath": "/qualification-oraclemastersilverdba",
            "pv": "5"
        },
        {
            "pagePath": "/game-ps5-mixamp-hdmiadapter/",
            "pv": "4"
        },
        {
            "pagePath": "/java-fibonacci-sequence/",
            "pv": "4"
        },
        {
            "pagePath": "/javasilver-se11-application",
            "pv": "4"
        },
        {
            "pagePath": "/qualification-aws-clf/",
            "pv": "4"
        },
        {
            "pagePath": "/qualification-ip-merit/",
            "pv": "4"
        },
        {
            "pagePath": "/game-trophy-2021-07-25/",
            "pv": "3"
        },
        {
            "pagePath": "/github-actions-autocommit/",
            "pv": "3"
        },
        {
            "pagePath": "/java-fizzbuzz/",
            "pv": "3"
        },
        {
            "pagePath": "/qualification-fe-kayanoki/",
            "pv": "3"
        },
        {
            "pagePath": "/qualification-sc/",
            "pv": "3"
        },
        {
            "pagePath": "/vmware-monitor/",
            "pv": "3"
        },
        {
            "pagePath": "/blog-alt-setting/",
            "pv": "2"
        },
        {
            "pagePath": "/c-language-compiler/",
            "pv": "2"
        },
        {
            "pagePath": "/java-browser-compile/",
            "pv": "2"
        },
        {
            "pagePath": "/java-magic-square-4-4/",
            "pv": "2"
        },
        {
            "pagePath": "/java-pow-method/",
            "pv": "2"
        },
        {
            "pagePath": "/product-review-shure-aonic215/",
            "pv": "2"
        },
        {
            "pagePath": "/qualification-ap-pass/",
            "pv": "2"
        },
        {
            "pagePath": "/qualification-ap-pm/",
            "pv": "2"
        },
        {
            "pagePath": "/qualification-fe-pm-selection/",
            "pv": "2"
        },
        {
            "pagePath": "/qualification-ip-pass/",
            "pv": "2"
        },
        {
            "pagePath": "/tags/fe",
            "pv": "2"
        },
        {
            "pagePath": "/adsense-copycontents/",
            "pv": "1"
        },
        {
            "pagePath": "/categories/it-qualification/",
            "pv": "1"
        },
        {
            "pagePath": "/java-islowercase-method",
            "pv": "1"
        },
        {
            "pagePath": "/java-localdate-period",
            "pv": "1"
        },
        {
            "pagePath": "/java-mini-numberplace-1/",
            "pv": "1"
        },
        {
            "pagePath": "/java-sqrt-method",
            "pv": "1"
        },
        {
            "pagePath": "/java-sudoku-1/",
            "pv": "1"
        },
        {
            "pagePath": "/product-review-logicool-k380/",
            "pv": "1"
        },
        {
            "pagePath": "/profile",
            "pv": "1"
        },
        {
            "pagePath": "/qualification-aws-saa",
            "pv": "1"
        },
        {
            "pagePath": "/qualification-fe-pass",
            "pv": "1"
        },
        {
            "pagePath": "/qualification-fe-pm-selection",
            "pv": "1"
        },
        {
            "pagePath": "/qualification-ip-merit",
            "pv": "1"
        },
        {
            "pagePath": "/qualification-sg-pass",
            "pv": "1"
        },
        {
            "pagePath": "/tags/ap/",
            "pv": "1"
        },
        {
            "pagePath": "/tags/sc/",
            "pv": "1"
        },
        {
            "pagePath": "/wordpress-mathjax/",
            "pv": "1"
        }
    ],
    "createdAt": "2024-11-21T02:52:26.195Z"
}